{"version":"1","data":[{"id":"cctv5","time":[{"start":1555441200,"end":1555447500,"url":""},{"start":1555527600,"end":1555533900,"url":""}]},{"id":"cctv5jiaHD","time":[{"start":1555441200,"end":1555447500,"url":""},{"start":1555527600,"end":1555533900,"url":""}]},{"id":"ws_jsty","time":[{"start":1555155300,"end":1555161300,"url":""}]},{"id":"chongqingshenghuozixun","time":[{"start":1554464113,"end":1554470100,"url":""}]},{"id":"hubeishenghuo","time":[{"start":1554032100,"end":1554038400,"url":""}]},{"id":"fyzq","time":[{"start":1555441200,"end":1555447500,"url":""},{"start":1555527600,"end":1555533900,"url":""}]},{"id":"ws_sztyjk","time":[{"start":1555155300,"end":1555161300,"url":""}]},{"id":"ws_gdty","time":[{"start":1555068900,"end":1555074900,"url":""}]},{"id":"wuhanwenti","time":[{"start":1555241700,"end":1555248000,"url":""}]},{"id":"hubeishenghuo","time":[{"start":1555241700,"end":1555248000,"url":""}]},{"id":"ws_hnxw","time":[{"start":1555241700,"end":1555248000,"url":""}]},{"id":"btv6","time":[{"start":1555227000,"end":1555233300,"url":""}]}]}
